{
  "series": [
    {
      "date": "2024-W14",
      "datasets": [
        {
          "datasetName": "flows",
          "values": {
            "volume": 32833164.093809035,
            "volume_gas": 2048295236.2038088,
            "mass": 25953628.983614,
            "energy": 834255821.8029907
          }
        }
      ],
      "periodEndDate": "2024-04-07T23:59:59.999Z"
    },
    {
      "date": "2024-W15",
      "datasets": [
        {
          "datasetName": "flows",
          "values": {
            "volume": 32327577.468410846,
            "volume_gas": 2235593213.1184106,
            "mass": 25547968.989660002,
            "energy": 820864884.1026957
          }
        }
      ],
      "periodEndDate": "2024-04-14T23:59:59.999Z"
    },
    {
      "date": "2024-W16",
      "datasets": [
        {
          "datasetName": "flows",
          "values": {
            "volume": 31062924.062876467,
            "volume_gas": 2132434700.3528762,
            "mass": 24716321.64265,
            "energy": 788756158.6824534
          }
        }
      ],
      "periodEndDate": "2024-04-21T23:59:59.999Z"
    },
    {
      "date": "2024-W17",
      "datasets": [
        {
          "datasetName": "flows",
          "values": {
            "volume": 31583936.63814842,
            "volume_gas": 1859350791.1681485,
            "mass": 25150089.217584003,
            "energy": 802565370.073132
          }
        }
      ],
      "periodEndDate": "2024-04-28T23:59:59.999Z"
    },
    {
      "date": "2024-W18",
      "datasets": [
        {
          "datasetName": "flows",
          "values": {
            "volume": 29799928.473614145,
            "volume_gas": 2138351286.673614,
            "mass": 23471458.0522,
            "energy": 756268244.4579298
          }
        }
      ],
      "periodEndDate": "2024-05-05T23:59:59.999Z"
    },
    {
      "date": "2024-W19",
      "datasets": [
        {
          "datasetName": "flows",
          "values": {
            "volume": 30188221.83401619,
            "volume_gas": 1971597536.094016,
            "mass": 23979868.67696,
            "energy": 766468888.5030614
          }
        }
      ],
      "periodEndDate": "2024-05-12T23:59:59.999Z"
    },
    {
      "date": "2024-W20",
      "datasets": [
        {
          "datasetName": "flows",
          "values": {
            "volume": 32008474.586284515,
            "volume_gas": 1709008675.8462844,
            "mass": 25607434.64816,
            "energy": 814041048.620646
          }
        }
      ],
      "periodEndDate": "2024-05-19T23:59:59.999Z"
    },
    {
      "date": "2024-W21",
      "datasets": [
        {
          "datasetName": "flows",
          "values": {
            "volume": 30608908.240810134,
            "volume_gas": 1600658444.28081,
            "mass": 24628686.725422,
            "energy": 778192816.4269779
          }
        }
      ],
      "periodEndDate": "2024-05-26T23:59:59.999Z"
    },
    {
      "date": "2024-W22",
      "datasets": [
        {
          "datasetName": "flows",
          "values": {
            "volume": 31516951.07099211,
            "volume_gas": 1839447806.8709922,
            "mass": 25183024.610990003,
            "energy": 800724768.530179
          }
        }
      ],
      "periodEndDate": "2024-06-02T23:59:59.999Z"
    },
    {
      "date": "2024-W23",
      "datasets": [
        {
          "datasetName": "flows",
          "values": {
            "volume": 27598779.000604544,
            "volume_gas": 2129195824.6056044,
            "mass": 21730024.27746,
            "energy": 699830554.136416
          }
        }
      ],
      "periodEndDate": "2024-06-09T23:59:59.999Z"
    },
    {
      "date": "2024-W24",
      "datasets": [
        {
          "datasetName": "flows",
          "values": {
            "volume": 32259709.30250096,
            "volume_gas": 1922608557.442501,
            "mass": 25832970.80148,
            "energy": 819742187.0379676
          }
        }
      ],
      "periodEndDate": "2024-06-16T23:59:59.999Z"
    },
    {
      "date": "2024-W25",
      "datasets": [
        {
          "datasetName": "flows",
          "values": {
            "volume": 28685087.048031233,
            "volume_gas": 1909944034.9380312,
            "mass": 22782735.38398,
            "energy": 728392553.2912363
          }
        }
      ],
      "periodEndDate": "2024-06-23T23:59:59.999Z"
    },
    {
      "date": "2024-W26",
      "datasets": [
        {
          "datasetName": "flows",
          "values": {
            "volume": 31123682.17947051,
            "volume_gas": 2064258046.1594706,
            "mass": 24629145.33475,
            "energy": 790655659.9657922
          }
        }
      ],
      "periodEndDate": "2024-06-30T23:59:59.999Z"
    },
    {
      "date": "2024-W27",
      "datasets": [
        {
          "datasetName": "flows",
          "values": {
            "volume": 30274316.803292498,
            "volume_gas": 2031367288.8532925,
            "mass": 23908243.69855,
            "energy": 768686165.4785224
          }
        }
      ],
      "periodEndDate": "2024-07-07T23:59:59.999Z"
    },
    {
      "date": "2024-W28",
      "datasets": [
        {
          "datasetName": "flows",
          "values": {
            "volume": 32115577.06575636,
            "volume_gas": 2208255592.4007564,
            "mass": 25554085.04812,
            "energy": 815515566.1054893
          }
        }
      ],
      "periodEndDate": "2024-07-14T23:59:59.999Z"
    },
    {
      "date": "2024-W29",
      "datasets": [
        {
          "datasetName": "flows",
          "values": {
            "volume": 32861849.518661045,
            "volume_gas": 2108579703.743661,
            "mass": 26043954.408570003,
            "energy": 834695720.6429049
          }
        }
      ],
      "periodEndDate": "2024-07-21T23:59:59.999Z"
    },
    {
      "date": "2024-W30",
      "datasets": [
        {
          "datasetName": "flows",
          "values": {
            "volume": 32560262.686240714,
            "volume_gas": 2054151646.8212407,
            "mass": 25807376.04062,
            "energy": 827151018.8153236
          }
        }
      ],
      "periodEndDate": "2024-07-28T23:59:59.999Z"
    },
    {
      "date": "2024-W31",
      "datasets": [
        {
          "datasetName": "flows",
          "values": {
            "volume": 30131352.850303393,
            "volume_gas": 1991330138.6253033,
            "mass": 23956616.31849,
            "energy": 765241937.9811842
          }
        }
      ],
      "periodEndDate": "2024-08-04T23:59:59.999Z"
    },
    {
      "date": "2024-W32",
      "datasets": [
        {
          "datasetName": "flows",
          "values": {
            "volume": 32447323.012748495,
            "volume_gas": 2068463726.0727484,
            "mass": 25738785.06832,
            "energy": 824560015.5675875
          }
        }
      ],
      "periodEndDate": "2024-08-11T23:59:59.999Z"
    },
    {
      "date": "2024-W33",
      "datasets": [
        {
          "datasetName": "flows",
          "values": {
            "volume": 34300632.86008025,
            "volume_gas": 2162913228.18508,
            "mass": 27426662.762039002,
            "energy": 871067632.3823582
          }
        }
      ],
      "periodEndDate": "2024-08-18T23:59:59.999Z"
    },
    {
      "date": "2024-W34",
      "datasets": [
        {
          "datasetName": "flows",
          "values": {
            "volume": 33097592.325281106,
            "volume_gas": 2022389424.2052808,
            "mass": 26420130.229728002,
            "energy": 841260541.5677913
          }
        }
      ],
      "periodEndDate": "2024-08-25T23:59:59.999Z"
    },
    {
      "date": "2024-W35",
      "datasets": [
        {
          "datasetName": "flows",
          "values": {
            "volume": 28226352.859452024,
            "volume_gas": 1922252668.014452,
            "mass": 22408717.019149,
            "energy": 716527000.6565087
          }
        }
      ],
      "periodEndDate": "2024-09-01T23:59:59.999Z"
    },
    {
      "date": "2024-W36",
      "datasets": [
        {
          "datasetName": "flows",
          "values": {
            "volume": 32287915.352227576,
            "volume_gas": 2030775131.9922273,
            "mass": 25761753.72929,
            "energy": 820283581.0657587
          }
        }
      ],
      "periodEndDate": "2024-09-08T23:59:59.999Z"
    },
    {
      "date": "2024-W37",
      "datasets": [
        {
          "datasetName": "flows",
          "values": {
            "volume": 29976259.180032127,
            "volume_gas": 1920797096.485032,
            "mass": 23959544.22608,
            "energy": 761439339.3169426
          }
        }
      ],
      "periodEndDate": "2024-09-15T23:59:59.999Z"
    },
    {
      "date": "2024-W38",
      "datasets": [
        {
          "datasetName": "flows",
          "values": {
            "volume": 36263042.96108877,
            "volume_gas": 2015041061.4360886,
            "mass": 29051795.038399998,
            "energy": 921584452.5686842
          }
        }
      ],
      "periodEndDate": "2024-09-22T23:59:59.999Z"
    },
    {
      "date": "2024-W39",
      "datasets": [
        {
          "datasetName": "flows",
          "values": {
            "volume": 30405861.939882316,
            "volume_gas": 2094570907.984882,
            "mass": 24102681.030424003,
            "energy": 772167968.2003607
          }
        }
      ],
      "periodEndDate": "2024-09-29T23:59:59.999Z"
    },
    {
      "date": "2024-W40",
      "datasets": [
        {
          "datasetName": "flows",
          "values": {
            "volume": 31226088.990814775,
            "volume_gas": 2014842252.7058146,
            "mass": 24942655.89692,
            "energy": 793282904.9226828
          }
        }
      ],
      "periodEndDate": "2024-10-06T23:59:59.999Z"
    },
    {
      "date": "2024-W41",
      "datasets": [
        {
          "datasetName": "flows",
          "values": {
            "volume": 33445043.05087334,
            "volume_gas": 2015918665.0108733,
            "mass": 26675844.22768,
            "energy": 849856594.616622
          }
        }
      ],
      "periodEndDate": "2024-10-13T23:59:59.999Z"
    },
    {
      "date": "2024-W42",
      "datasets": [
        {
          "datasetName": "flows",
          "values": {
            "volume": 30902940.448434066,
            "volume_gas": 2034956816.428434,
            "mass": 24444564.60218,
            "energy": 784798245.7004989
          }
        }
      ],
      "periodEndDate": "2024-10-20T23:59:59.999Z"
    },
    {
      "date": "2024-W43",
      "datasets": [
        {
          "datasetName": "flows",
          "values": {
            "volume": 28513152.533268224,
            "volume_gas": 1520460184.903268,
            "mass": 22995424.952260002,
            "energy": 725130135.5391726
          }
        }
      ],
      "periodEndDate": "2024-10-27T23:59:59.999Z"
    },
    {
      "date": "2024-W44",
      "datasets": [
        {
          "datasetName": "flows",
          "values": {
            "volume": 29948105.417189162,
            "volume_gas": 1843398608.1671891,
            "mass": 23963691.7574,
            "energy": 760934941.5291982
          }
        }
      ],
      "periodEndDate": "2024-11-03T23:59:59.999Z"
    },
    {
      "date": "2024-W45",
      "datasets": [
        {
          "datasetName": "flows",
          "values": {
            "volume": 31606190.50852164,
            "volume_gas": 1664036357.3485215,
            "mass": 25267235.68248,
            "energy": 803703378.5593741
          }
        }
      ],
      "periodEndDate": "2024-11-10T23:59:59.999Z"
    },
    {
      "date": "2024-W46",
      "datasets": [
        {
          "datasetName": "flows",
          "values": {
            "volume": 32467743.166973054,
            "volume_gas": 2088045013.991973,
            "mass": 26002101.023819998,
            "energy": 824922690.4710323
          }
        }
      ],
      "periodEndDate": "2024-11-17T23:59:59.999Z"
    },
    {
      "date": "2024-W47",
      "datasets": [
        {
          "datasetName": "flows",
          "values": {
            "volume": 33159256.496844266,
            "volume_gas": 2171519409.056844,
            "mass": 26374437.26351,
            "energy": 842368686.4182788
          }
        }
      ],
      "periodEndDate": "2024-11-24T23:59:59.999Z"
    },
    {
      "date": "2024-W48",
      "datasets": [
        {
          "datasetName": "flows",
          "values": {
            "volume": 28977705.31705056,
            "volume_gas": 2262735029.6070504,
            "mass": 22921443.457655,
            "energy": 735546819.3050698
          }
        }
      ],
      "periodEndDate": "2024-12-01T23:59:59.999Z"
    },
    {
      "date": "2024-W49",
      "datasets": [
        {
          "datasetName": "flows",
          "values": {
            "volume": 33671369.186208986,
            "volume_gas": 1987869991.051209,
            "mass": 26957263.35954,
            "energy": 855766722.5044332
          }
        }
      ],
      "periodEndDate": "2024-12-08T23:59:59.999Z"
    },
    {
      "date": "2024-W50",
      "datasets": [
        {
          "datasetName": "flows",
          "values": {
            "volume": 31896078.67555003,
            "volume_gas": 2246784066.6826,
            "mass": 25228184.115089998,
            "energy": 809953724.9272357
          }
        }
      ],
      "periodEndDate": "2024-12-15T23:59:59.999Z"
    },
    {
      "date": "2024-W51",
      "datasets": [
        {
          "datasetName": "flows",
          "values": {
            "volume": 33003366.369604077,
            "volume_gas": 2111059340.9296038,
            "mass": 26166622.471435,
            "energy": 838489949.177849
          }
        }
      ],
      "periodEndDate": "2024-12-22T23:59:59.999Z"
    },
    {
      "date": "2024-W52",
      "datasets": [
        {
          "datasetName": "flows",
          "values": {
            "volume": 32526070.558622267,
            "volume_gas": 2056497615.703622,
            "mass": 26012200.449521,
            "energy": 826397342.8211036
          }
        }
      ],
      "periodEndDate": "2024-12-29T23:59:59.999Z"
    },
    {
      "date": "2025-W01",
      "datasets": [
        {
          "datasetName": "flows",
          "values": {
            "volume": 29458467.27479,
            "volume_gas": 2156561508.21979,
            "mass": 23225460.712358,
            "energy": 747850048.7631595
          }
        }
      ],
      "periodEndDate": "2025-01-05T23:59:59.999Z"
    },
    {
      "date": "2025-W02",
      "datasets": [
        {
          "datasetName": "flows",
          "values": {
            "volume": 33462420.59306714,
            "volume_gas": 2043526295.2880669,
            "mass": 26733658.451959,
            "energy": 850366784.7095255
          }
        }
      ],
      "periodEndDate": "2025-01-12T23:59:59.999Z"
    },
    {
      "date": "2025-W03",
      "datasets": [
        {
          "datasetName": "flows",
          "values": {
            "volume": 30212127.60398153,
            "volume_gas": 2336239073.6689816,
            "mass": 23744013.0784,
            "energy": 766909358.8550069
          }
        }
      ],
      "periodEndDate": "2025-01-19T23:59:59.999Z"
    },
    {
      "date": "2025-W04",
      "datasets": [
        {
          "datasetName": "flows",
          "values": {
            "volume": 33957724.42618401,
            "volume_gas": 2218526212.061184,
            "mass": 26987009.025794998,
            "energy": 862672095.6368589
          }
        }
      ],
      "periodEndDate": "2025-01-26T23:59:59.999Z"
    },
    {
      "date": "2025-W05",
      "datasets": [
        {
          "datasetName": "flows",
          "values": {
            "volume": 33323119.911764707,
            "volume_gas": 2367055843.2117643,
            "mass": 26322144.65568,
            "energy": 845361696.2666354
          }
        }
      ],
      "periodEndDate": "2025-02-02T23:59:59.999Z"
    },
    {
      "date": "2025-W06",
      "datasets": [
        {
          "datasetName": "flows",
          "values": {
            "volume": 30531796.88438894,
            "volume_gas": 1990589295.5043888,
            "mass": 24075659.356370002,
            "energy": 775467843.8469045
          }
        }
      ],
      "periodEndDate": "2025-02-09T23:59:59.999Z"
    },
    {
      "date": "2025-W07",
      "datasets": [
        {
          "datasetName": "flows",
          "values": {
            "volume": 33007741.73174963,
            "volume_gas": 2358214530.2367496,
            "mass": 26113353.77263,
            "energy": 838116456.4583246
          }
        }
      ],
      "periodEndDate": "2025-02-16T23:59:59.999Z"
    },
    {
      "date": "2025-W08",
      "datasets": [
        {
          "datasetName": "flows",
          "values": {
            "volume": 30378991.442251682,
            "volume_gas": 2043121655.8622515,
            "mass": 24050146.548662,
            "energy": 771604878.0332481
          }
        }
      ],
      "periodEndDate": "2025-02-23T23:59:59.999Z"
    },
    {
      "date": "2025-W09",
      "datasets": [
        {
          "datasetName": "flows",
          "values": {
            "volume": 29908813.861910693,
            "volume_gas": 2222886080.046911,
            "mass": 23649726.336606,
            "energy": 759236579.2069017
          }
        }
      ],
      "periodEndDate": "2025-03-02T23:59:59.999Z"
    },
    {
      "date": "2025-W10",
      "datasets": [
        {
          "datasetName": "flows",
          "values": {
            "volume": 30187648.19760597,
            "volume_gas": 2197057769.442606,
            "mass": 23583687.99099,
            "energy": 766376869.2906646
          }
        }
      ],
      "periodEndDate": "2025-03-09T23:59:59.999Z"
    },
    {
      "date": "2025-W11",
      "datasets": [
        {
          "datasetName": "flows",
          "values": {
            "volume": 34334487.15762573,
            "volume_gas": 2107775512.3376255,
            "mass": 27302501.14195,
            "energy": 872158458.9483535
          }
        }
      ],
      "periodEndDate": "2025-03-16T23:59:59.999Z"
    },
    {
      "date": "2025-W12",
      "datasets": [
        {
          "datasetName": "flows",
          "values": {
            "volume": 29302707.724785693,
            "volume_gas": 2025735885.1647856,
            "mass": 23235892.024706,
            "energy": 744114515.7110744
          }
        }
      ],
      "periodEndDate": "2025-03-23T23:59:59.999Z"
    },
    {
      "date": "2025-W13",
      "datasets": [
        {
          "datasetName": "flows",
          "values": {
            "volume": 33111559.279497202,
            "volume_gas": 2240876289.494497,
            "mass": 26322737.40943,
            "energy": 841013036.2167494
          }
        }
      ],
      "periodEndDate": "2025-03-30T23:59:59.999Z"
    },
    {
      "date": "2025-W14",
      "datasets": [
        {
          "datasetName": "flows",
          "values": {
            "volume": 32867043.750787713,
            "volume_gas": 2160157482.7007875,
            "mass": 26014283.105226,
            "energy": 833947599.186779
          }
        }
      ],
      "periodEndDate": "2025-04-06T23:59:59.999Z"
    },
    {
      "date": "2025-W15",
      "datasets": [
        {
          "datasetName": "flows",
          "values": {
            "volume": 30315747.039180744,
            "volume_gas": 1960976905.2591805,
            "mass": 24262681.895568,
            "energy": 770107514.3456465
          }
        }
      ],
      "periodEndDate": "2025-04-13T23:59:59.999Z"
    },
    {
      "date": "2025-W16",
      "datasets": [
        {
          "datasetName": "flows",
          "values": {
            "volume": 27423113.203206763,
            "volume_gas": 1714483351.2282066,
            "mass": 21819611.55128,
            "energy": 696295846.4146574
          }
        }
      ],
      "periodEndDate": "2025-04-20T23:59:59.999Z"
    },
    {
      "date": "2025-W17",
      "datasets": [
        {
          "datasetName": "flows",
          "values": {
            "volume": 32692998.46154962,
            "volume_gas": 2093165979.4565496,
            "mass": 26135767.6521,
            "energy": 830521334.9615371
          }
        }
      ],
      "periodEndDate": "2025-04-27T23:59:59.999Z"
    },
    {
      "date": "2025-W18",
      "datasets": [
        {
          "datasetName": "flows",
          "values": {
            "volume": 32855562.47411814,
            "volume_gas": 1682571322.614118,
            "mass": 26382326.702290002,
            "energy": 835516168.2432046
          }
        }
      ],
      "periodEndDate": "2025-05-04T23:59:59.999Z"
    },
    {
      "date": "2025-W19",
      "datasets": [
        {
          "datasetName": "flows",
          "values": {
            "volume": 30150987.974832643,
            "volume_gas": 2393336899.8298326,
            "mass": 23624074.968452,
            "energy": 764945316.8190153
          }
        }
      ],
      "periodEndDate": "2025-05-11T23:59:59.999Z"
    },
    {
      "date": "2025-W20",
      "datasets": [
        {
          "datasetName": "flows",
          "values": {
            "volume": 34217080.273396775,
            "volume_gas": 2031283427.2133965,
            "mass": 27183395.777111,
            "energy": 869437207.1578015
          }
        }
      ],
      "periodEndDate": "2025-05-18T23:59:59.999Z"
    },
    {
      "date": "2025-W21",
      "datasets": [
        {
          "datasetName": "flows",
          "values": {
            "volume": 30807691.853874125,
            "volume_gas": 1920670195.8338742,
            "mass": 24584289.727391,
            "energy": 782786280.413862
          }
        }
      ],
      "periodEndDate": "2025-05-25T23:59:59.999Z"
    },
    {
      "date": "2025-W22",
      "datasets": [
        {
          "datasetName": "flows",
          "values": {
            "volume": 28253461.583062965,
            "volume_gas": 1975794776.6080627,
            "mass": 22254467.49304,
            "energy": 717408043.8843
          }
        }
      ],
      "periodEndDate": "2025-06-01T23:59:59.999Z"
    },
    {
      "date": "2025-W23",
      "datasets": [
        {
          "datasetName": "flows",
          "values": {
            "volume": 33597280.639055654,
            "volume_gas": 2125328860.1540556,
            "mass": 26846006.832994,
            "energy": 853821716.7733119
          }
        }
      ],
      "periodEndDate": "2025-06-08T23:59:59.999Z"
    },
    {
      "date": "2025-W24",
      "datasets": [
        {
          "datasetName": "flows",
          "values": {
            "volume": 36083749.54506791,
            "volume_gas": 2210503474.380068,
            "mass": 28691721.515338,
            "energy": 916672219.713695
          }
        }
      ],
      "periodEndDate": "2025-06-15T23:59:59.999Z"
    },
    {
      "date": "2025-W25",
      "datasets": [
        {
          "datasetName": "flows",
          "values": {
            "volume": 31145564.76962614,
            "volume_gas": 1990733365.234626,
            "mass": 24848282.76287,
            "energy": 789461689.1126878
          }
        }
      ],
      "periodEndDate": "2025-06-22T23:59:59.999Z"
    },
    {
      "date": "2025-W26",
      "datasets": [
        {
          "datasetName": "flows",
          "values": {
            "volume": 31056272.184278246,
            "volume_gas": 2192522091.629278,
            "mass": 24582155.120808,
            "energy": 788257164.502863
          }
        }
      ],
      "periodEndDate": "2025-06-29T23:59:59.999Z"
    },
    {
      "date": "2025-W27",
      "datasets": [
        {
          "datasetName": "flows",
          "values": {
            "volume": 31909308.47521067,
            "volume_gas": 1960230739.6302106,
            "mass": 25370546.349797003,
            "energy": 810883924.7071741
          }
        }
      ],
      "periodEndDate": "2025-07-06T23:59:59.999Z"
    },
    {
      "date": "2025-W28",
      "datasets": [
        {
          "datasetName": "flows",
          "values": {
            "volume": 31920271.379188534,
            "volume_gas": 1878683750.1341884,
            "mass": 25618657.375084,
            "energy": 811472731.0316347
          }
        }
      ],
      "periodEndDate": "2025-07-13T23:59:59.999Z"
    },
    {
      "date": "2025-W29",
      "datasets": [
        {
          "datasetName": "flows",
          "values": {
            "volume": 32908264.890562575,
            "volume_gas": 2276297075.9755626,
            "mass": 26156237.03833,
            "energy": 835432102.748362
          }
        }
      ],
      "periodEndDate": "2025-07-20T23:59:59.999Z"
    },
    {
      "date": "2025-W30",
      "datasets": [
        {
          "datasetName": "flows",
          "values": {
            "volume": 31359914.443971954,
            "volume_gas": 2084534366.9539719,
            "mass": 24908791.360106,
            "energy": 796648410.5782024
          }
        }
      ],
      "periodEndDate": "2025-07-27T23:59:59.999Z"
    },
    {
      "date": "2025-W31",
      "datasets": [
        {
          "datasetName": "flows",
          "values": {
            "volume": 30459477.32481204,
            "volume_gas": 1889314777.249812,
            "mass": 24267927.075158,
            "energy": 773748639.5779798
          }
        }
      ],
      "periodEndDate": "2025-08-03T23:59:59.999Z"
    },
    {
      "date": "2025-W32",
      "datasets": [
        {
          "datasetName": "flows",
          "values": {
            "volume": 34207208.72509414,
            "volume_gas": 2253539396.2600937,
            "mass": 27115045.10082,
            "energy": 868937949.661509
          }
        }
      ],
      "periodEndDate": "2025-08-10T23:59:59.999Z"
    },
    {
      "date": "2025-W33",
      "datasets": [
        {
          "datasetName": "flows",
          "values": {
            "volume": 32807401.24046793,
            "volume_gas": 1965185955.1804678,
            "mass": 26264143.72793,
            "energy": 833692696.2994336
          }
        }
      ],
      "periodEndDate": "2025-08-17T23:59:59.999Z"
    },
    {
      "date": "2025-W34",
      "datasets": [
        {
          "datasetName": "flows",
          "values": {
            "volume": 30033158.06215627,
            "volume_gas": 1582301288.9571562,
            "mass": 24019826.478166,
            "energy": 763855497.4203361
          }
        }
      ],
      "periodEndDate": "2025-08-24T23:59:59.999Z"
    },
    {
      "date": "2025-W35",
      "datasets": [
        {
          "datasetName": "flows",
          "values": {
            "volume": 32103299.218607545,
            "volume_gas": 1823233270.6686072,
            "mass": 25713159.160967,
            "energy": 816234943.4486195
          }
        }
      ],
      "periodEndDate": "2025-08-31T23:59:59.999Z"
    },
    {
      "date": "2025-W36",
      "datasets": [
        {
          "datasetName": "flows",
          "values": {
            "volume": 32682430.193542488,
            "volume_gas": 2082143350.8685422,
            "mass": 26166303.137456,
            "energy": 830116722.3738164
          }
        }
      ],
      "periodEndDate": "2025-09-07T23:59:59.999Z"
    },
    {
      "date": "2025-W37",
      "datasets": [
        {
          "datasetName": "flows",
          "values": {
            "volume": 32543513.04065507,
            "volume_gas": 1608642241.595655,
            "mass": 26118313.379704,
            "energy": 827733746.6189406
          }
        }
      ],
      "periodEndDate": "2025-09-14T23:59:59.999Z"
    },
    {
      "date": "2025-W38",
      "datasets": [
        {
          "datasetName": "flows",
          "values": {
            "volume": 34847331.497144945,
            "volume_gas": 2219387712.217145,
            "mass": 27684894.461516,
            "energy": 885539156.4133167
          }
        }
      ],
      "periodEndDate": "2025-09-21T23:59:59.999Z"
    },
    {
      "date": "2025-W39",
      "datasets": [
        {
          "datasetName": "flows",
          "values": {
            "volume": 33058870.804151725,
            "volume_gas": 1842154125.3241515,
            "mass": 26311704.348675,
            "energy": 840628908.9847915
          }
        }
      ],
      "periodEndDate": "2025-09-28T23:59:59.999Z"
    },
    {
      "date": "2025-W40",
      "datasets": [
        {
          "datasetName": "flows",
          "values": {
            "volume": 32893768.282745548,
            "volume_gas": 1654282737.3527455,
            "mass": 26558111.826863,
            "energy": 836852969.3799613
          }
        }
      ],
      "periodEndDate": "2025-10-05T23:59:59.999Z"
    },
    {
      "date": "2025-W41",
      "datasets": [
        {
          "datasetName": "flows",
          "values": {
            "volume": 32065296.327818178,
            "volume_gas": 2305239497.097818,
            "mass": 25535417.680046,
            "energy": 814082096.8602985
          }
        }
      ],
      "periodEndDate": "2025-10-12T23:59:59.999Z"
    },
    {
      "date": "2025-W42",
      "datasets": [
        {
          "datasetName": "flows",
          "values": {
            "volume": 31568818.38873533,
            "volume_gas": 1639499796.6687353,
            "mass": 25464881.23643,
            "energy": 802969004.548268
          }
        }
      ],
      "periodEndDate": "2025-10-19T23:59:59.999Z"
    },
    {
      "date": "2025-W43",
      "datasets": [
        {
          "datasetName": "flows",
          "values": {
            "volume": 33068759.315426406,
            "volume_gas": 2028045259.2604263,
            "mass": 26445517.952735,
            "energy": 840469691.5326755
          }
        }
      ],
      "periodEndDate": "2025-10-26T23:59:59.999Z"
    },
    {
      "date": "2025-W44",
      "datasets": [
        {
          "datasetName": "flows",
          "values": {
            "volume": 31888068.886642262,
            "volume_gas": 2035258218.1966422,
            "mass": 25362659.567412,
            "energy": 810338946.9973006
          }
        }
      ],
      "periodEndDate": "2025-11-02T23:59:59.999Z"
    },
    {
      "date": "2025-W45",
      "datasets": [
        {
          "datasetName": "flows",
          "values": {
            "volume": 33906266.489584394,
            "volume_gas": 2145271917.6995845,
            "mass": 26952549.26117,
            "energy": 861674911.5431166
          }
        }
      ],
      "periodEndDate": "2025-11-09T23:59:59.999Z"
    },
    {
      "date": "2025-W46",
      "datasets": [
        {
          "datasetName": "flows",
          "values": {
            "volume": 33020040.595944233,
            "volume_gas": 1795313084.2509441,
            "mass": 26521156.294744,
            "energy": 839731219.1123286
          }
        }
      ],
      "periodEndDate": "2025-11-16T23:59:59.999Z"
    },
    {
      "date": "2025-W47",
      "datasets": [
        {
          "datasetName": "flows",
          "values": {
            "volume": 32278600.776387878,
            "volume_gas": 1966024784.6113877,
            "mass": 25908474.36529,
            "energy": 820452999.3168854
          }
        }
      ],
      "periodEndDate": "2025-11-23T23:59:59.999Z"
    },
    {
      "date": "2025-W48",
      "datasets": [
        {
          "datasetName": "flows",
          "values": {
            "volume": 33053541.74409042,
            "volume_gas": 2186191840.7640905,
            "mass": 26345688.785606,
            "energy": 839611583.1245654
          }
        }
      ],
      "periodEndDate": "2025-11-30T23:59:59.999Z"
    },
    {
      "date": "2025-W49",
      "datasets": [
        {
          "datasetName": "flows",
          "values": {
            "volume": 32056977.052738648,
            "volume_gas": 1814383958.4427385,
            "mass": 25636289.80736,
            "energy": 815092918.8848516
          }
        }
      ],
      "periodEndDate": "2025-12-07T23:59:59.999Z"
    },
    {
      "date": "2025-W50",
      "datasets": [
        {
          "datasetName": "flows",
          "values": {
            "volume": 31696722.706774514,
            "volume_gas": 2174955541.0367746,
            "mass": 25238879.037792,
            "energy": 805001229.253589
          }
        }
      ],
      "periodEndDate": "2025-12-14T23:59:59.999Z"
    },
    {
      "date": "2025-W51",
      "datasets": [
        {
          "datasetName": "flows",
          "values": {
            "volume": 29055328.40342227,
            "volume_gas": 2094095631.1434221,
            "mass": 22954456.941302,
            "energy": 737663950.1657671
          }
        }
      ],
      "periodEndDate": "2025-12-21T23:59:59.999Z"
    },
    {
      "date": "2025-W52",
      "datasets": [
        {
          "datasetName": "flows",
          "values": {
            "volume": 33930470.08798137,
            "volume_gas": 2155661941.607981,
            "mass": 27045317.84496,
            "energy": 857500402.6373248
          }
        }
      ],
      "periodEndDate": "2025-12-28T23:59:59.999Z"
    },
    {
      "date": "2026-W01",
      "datasets": [
        {
          "datasetName": "flows",
          "values": {
            "volume": 33789130.22330728,
            "volume_gas": 2127378633.6033072,
            "mass": 26971636.239272,
            "energy": 857736739.9368689
          }
        }
      ],
      "periodEndDate": "2026-01-04T23:59:59.999Z"
    },
    {
      "date": "2026-W02",
      "datasets": [
        {
          "datasetName": "flows",
          "values": {
            "volume": 30939931.59046651,
            "volume_gas": 2141175222.8454664,
            "mass": 24531349.28757,
            "energy": 785710966.8983487
          }
        }
      ],
      "periodEndDate": "2026-01-11T23:59:59.999Z"
    },
    {
      "date": "2026-W03",
      "datasets": [
        {
          "datasetName": "flows",
          "values": {
            "volume": 30102375.285253514,
            "volume_gas": 2222852647.8152533,
            "mass": 23797198.480892,
            "energy": 764354500.6142871
          }
        }
      ],
      "periodEndDate": "2026-01-18T23:59:59.999Z"
    },
    {
      "date": "2026-W04",
      "datasets": [
        {
          "datasetName": "flows",
          "values": {
            "volume": 31893588.17004955,
            "volume_gas": 2169490897.0550494,
            "mass": 25406278.11606,
            "energy": 810014646.9684246
          }
        }
      ],
      "periodEndDate": "2026-01-25T23:59:59.999Z"
    },
    {
      "date": "2026-W05",
      "datasets": [
        {
          "datasetName": "flows",
          "values": {
            "volume": 32275233.42788115,
            "volume_gas": 2138178876.767881,
            "mass": 25667642.23445,
            "energy": 819852942.8793184
          }
        }
      ],
      "periodEndDate": "2026-02-01T23:59:59.999Z"
    },
    {
      "date": "2026-W06",
      "datasets": [
        {
          "datasetName": "flows",
          "values": {
            "volume": 30967301.197604064,
            "volume_gas": 2226527703.9676037,
            "mass": 24358983.431661,
            "energy": 786267997.8268836
          }
        }
      ],
      "periodEndDate": "2026-02-08T23:59:59.999Z"
    },
    {
      "date": "2026-W07",
      "datasets": [
        {
          "datasetName": "flows",
          "values": {
            "volume": 32304332.974789917,
            "volume_gas": 1964484460.86479,
            "mass": 25804973.023893,
            "energy": 821113684.2574854
          }
        }
      ],
      "periodEndDate": "2026-02-15T23:59:59.999Z"
    },
    {
      "date": "2026-W08",
      "datasets": [
        {
          "datasetName": "flows",
          "values": {
            "volume": 30984012.232593037,
            "volume_gas": 2313674062.202593,
            "mass": 24607348.78961,
            "energy": 786195083.2938967
          }
        }
      ],
      "periodEndDate": "2026-02-22T23:59:59.999Z"
    },
    {
      "date": "2026-W09",
      "datasets": [
        {
          "datasetName": "flows",
          "values": {
            "volume": 19606637.94539934,
            "volume_gas": 1255030917.7003994,
            "mass": 15570629.662431,
            "energy": 498148450.5685947
          }
        }
      ],
      "periodEndDate": "2026-03-01T23:59:59.999Z"
    },
    {
      "date": "2026-W10",
      "datasets": [
        {
          "datasetName": "flows",
          "values": {
            "volume": 2995713.9687152454,
            "volume_gas": 3010760.9737152453,
            "mass": 2447311.72115,
            "energy": 76516524.52044293
          }
        }
      ],
      "periodEndDate": "2026-03-08T23:59:59.999Z"
    },
    {
      "date": "2026-W11",
      "datasets": [
        {
          "datasetName": "flows",
          "values": {
            "volume": 1885072.799519808,
            "volume_gas": 1887473.669519808,
            "mass": 1620440.247,
            "energy": 48148528.3954317
          }
        }
      ],
      "periodEndDate": "2026-03-15T23:59:59.999Z"
    },
    {
      "date": "2026-W12",
      "datasets": [
        {
          "datasetName": "flows",
          "values": {
            "volume": 2248286.3865546216,
            "volume_gas": 2251573.9865546217,
            "mass": 1905530.2030000002,
            "energy": 57425729.63318081
          }
        }
      ],
      "periodEndDate": "2026-03-22T23:59:59.999Z"
    },
    {
      "date": "2026-W13",
      "datasets": [
        {
          "datasetName": "flows",
          "values": {
            "volume": 1156534.731092437,
            "volume_gas": 1161362.051092437,
            "mass": 952022.635,
            "energy": 29540209.457423687
          }
        }
      ],
      "periodEndDate": "2026-03-29T23:59:59.999Z"
    },
    {
      "date": "2026-W14",
      "datasets": [
        {
          "datasetName": "flows",
          "values": {
            "volume": 170876,
            "volume_gas": 170876,
            "mass": 141296.845,
            "energy": 4364514.6968295295
          }
        }
      ],
      "periodEndDate": "2026-04-05T23:59:59.999Z"
    }
  ],
  "metadata": null
}