{
  "insideTotal": 705,
  "insideBallast": 298,
  "insideLaden": 406,
  "outsideTotal": 334,
  "outsideBallast": 215,
  "outsideLaden": 119,
  "adnocCount": 11,
  "totalVessels": 1039,
  "transitCount": 13,
  "syncTimestamp": "2026-04-03T06:26:10.931Z",
  "deltaLabel": "24h",
  "deltas": {
    "insideDelta": -5,
    "outsideDelta": 15,
    "adnocDelta": 0,
    "insideBallastDelta": -4,
    "insideLadenDelta": -1,
    "outsideBallastDelta": 3,
    "outsideLadenDelta": 12,
    "exitedSinceMidnight": 2,
    "enteredSinceMidnight": 1
  },
  "smallVessels": {
    "inside": 132,
    "outside": 144,
    "total": 276,
    "types": [
      "Short Sea Tankers",
      "Small Tankers",
      "Mini Bulker"
    ]
  }
}