{
  "china_kero_jet": [
    "No significant jet/kerosene imports recorded for China in recent weeks."
  ],
  "china_gasoline": [
    "No significant gasoline imports recorded for China in recent weeks."
  ],
  "india_kero_jet": [
    "No significant jet/kerosene imports recorded for India in recent weeks."
  ],
  "japan_sulphur": [
    "No significant sulphur imports recorded for Japan in recent weeks."
  ],
  "south_korea_kero_jet": [
    "No significant jet/kerosene imports recorded for South Korea in recent weeks."
  ],
  "south_korea_sulphur": [
    "No significant sulphur imports recorded for South Korea in recent weeks."
  ],
  "thailand_kero_jet": [
    "No significant jet/kerosene imports recorded for Thailand in recent weeks."
  ],
  "thailand_sulphur": [
    "No significant sulphur imports recorded for Thailand in recent weeks."
  ],
  "vietnam_lng": [
    "No significant LNG imports recorded for Vietnam in recent weeks."
  ],
  "vietnam_naphtha": [
    "No significant naphtha imports recorded for Vietnam in recent weeks."
  ],
  "eu_27_lng": [
    "No significant LNG exports recorded for EU-27 in recent weeks."
  ],
  "eu_27_sulphur": [
    "No significant sulphur exports recorded for EU-27 in recent weeks."
  ],
  "united_states_lng": [
    "No significant LNG imports recorded for United States in recent weeks."
  ],
  "united_states_sulphur": [
    "No significant sulphur imports recorded for United States in recent weeks."
  ],
  "taiwan_lpg": [
    "No significant LPG imports recorded for Taiwan in recent weeks."
  ],
  "taiwan_kero_jet": [
    "No significant jet/kerosene imports recorded for Taiwan in recent weeks."
  ],
  "taiwan_sulphur": [
    "No significant sulphur imports recorded for Taiwan in recent weeks."
  ],
  "bahrain_crude": [
    "No significant crude oil exports recorded for Bahrain in recent weeks."
  ],
  "bahrain_lng": [
    "No significant LNG exports recorded for Bahrain in recent weeks."
  ],
  "bahrain_lpg": [
    "No significant LPG exports recorded for Bahrain in recent weeks."
  ],
  "bahrain_kero_jet": [
    "No significant jet/kerosene exports recorded for Bahrain in recent weeks."
  ],
  "bahrain_gasoil_diesel": [
    "No significant gasoil/diesel exports recorded for Bahrain in recent weeks."
  ],
  "bahrain_gasoline": [
    "No significant gasoline exports recorded for Bahrain in recent weeks."
  ],
  "bahrain_naphtha": [
    "No significant naphtha exports recorded for Bahrain in recent weeks."
  ],
  "bahrain_sulphur": [
    "No significant sulphur exports recorded for Bahrain in recent weeks."
  ],
  "iran_lng": [
    "No significant LNG exports recorded for Iran in recent weeks."
  ],
  "iran_kero_jet": [
    "No significant jet/kerosene exports recorded for Iran in recent weeks."
  ],
  "iran_gasoil_diesel": [
    "No significant gasoil/diesel exports recorded for Iran in recent weeks."
  ],
  "iran_gasoline": [
    "No significant gasoline exports recorded for Iran in recent weeks."
  ],
  "iran_naphtha": [
    "No significant naphtha exports recorded for Iran in recent weeks."
  ],
  "iran_sulphur": [
    "No significant sulphur exports recorded for Iran in recent weeks."
  ],
  "iraq_lng": [
    "No significant LNG exports recorded for Iraq in recent weeks."
  ],
  "iraq_lpg": [
    "No significant LPG exports recorded for Iraq in recent weeks."
  ],
  "iraq_kero_jet": [
    "No significant jet/kerosene exports recorded for Iraq in recent weeks."
  ],
  "iraq_gasoil_diesel": [
    "No significant gasoil/diesel exports recorded for Iraq in recent weeks."
  ],
  "iraq_gasoline": [
    "No significant gasoline exports recorded for Iraq in recent weeks."
  ],
  "iraq_sulphur": [
    "No significant sulphur exports recorded for Iraq in recent weeks."
  ],
  "kuwait_lng": [
    "No significant LNG exports recorded for Kuwait in recent weeks."
  ],
  "kuwait_lpg": [
    "No significant LPG exports recorded for Kuwait in recent weeks."
  ],
  "kuwait_kero_jet": [
    "No significant jet/kerosene exports recorded for Kuwait in recent weeks."
  ],
  "kuwait_gasoil_diesel": [
    "No significant gasoil/diesel exports recorded for Kuwait in recent weeks."
  ],
  "kuwait_gasoline": [
    "No significant gasoline exports recorded for Kuwait in recent weeks."
  ],
  "kuwait_naphtha": [
    "No significant naphtha exports recorded for Kuwait in recent weeks."
  ],
  "oman_lpg": [
    "No significant LPG exports recorded for Oman in recent weeks."
  ],
  "oman_naphtha": [
    "No significant naphtha exports recorded for Oman in recent weeks."
  ],
  "oman_sulphur": [
    "No significant sulphur exports recorded for Oman in recent weeks."
  ],
  "qatar_lpg": [
    "No significant LPG exports recorded for Qatar in recent weeks."
  ],
  "qatar_kero_jet": [
    "No significant jet/kerosene exports recorded for Qatar in recent weeks."
  ],
  "qatar_gasoil_diesel": [
    "No significant gasoil/diesel exports recorded for Qatar in recent weeks."
  ],
  "qatar_gasoline": [
    "No significant gasoline exports recorded for Qatar in recent weeks."
  ],
  "qatar_naphtha": [
    "No significant naphtha exports recorded for Qatar in recent weeks."
  ],
  "russia_kero_jet": [
    "No significant jet/kerosene exports recorded for Russia in recent weeks."
  ],
  "russia_gasoline": [
    "No significant gasoline exports recorded for Russia in recent weeks."
  ],
  "saudi_arabia_lng": [
    "No significant LNG exports recorded for Saudi Arabia in recent weeks."
  ],
  "uae_lng": [
    "No significant LNG exports recorded for Uae in recent weeks."
  ],
  "uae_lpg": [
    "No significant LPG exports recorded for Uae in recent weeks."
  ],
  "uae_kero_jet": [
    "No significant jet/kerosene exports recorded for Uae in recent weeks."
  ],
  "uae_gasoil_diesel": [
    "No significant gasoil/diesel exports recorded for Uae in recent weeks."
  ],
  "uae_gasoline": [
    "No significant gasoline exports recorded for Uae in recent weeks."
  ],
  "uae_sulphur": [
    "No significant sulphur exports recorded for Uae in recent weeks."
  ],
  "australia_kero_jet": [
    "No significant jet/kerosene exports recorded for Australia in recent weeks."
  ],
  "australia_gasoil_diesel": [
    "No significant gasoil/diesel exports recorded for Australia in recent weeks."
  ],
  "australia_gasoline": [
    "No significant gasoline exports recorded for Australia in recent weeks."
  ],
  "australia_sulphur": [
    "No significant sulphur exports recorded for Australia in recent weeks."
  ]
}